caravel_cocotb/__init__.py
caravel_cocotb/__main__.py
caravel_cocotb/__version__.py
caravel_cocotb/caravel_interfaces.py
caravel_cocotb/vip.py
caravel_cocotb/VIP/register_file.py
caravel_cocotb/VIP/wishbone.py
caravel_cocotb/interfaces/SPI.py
caravel_cocotb/interfaces/UART.py
caravel_cocotb/interfaces/caravel.py
caravel_cocotb/interfaces/common.py
caravel_cocotb/interfaces/cpu.py
caravel_cocotb/interfaces/defsParser.py
caravel_cocotb/interfaces/logic_analyzer.py
caravel_cocotb/interfaces/common_functions/Timeout.py
caravel_cocotb/interfaces/common_functions/bitbang.h
caravel_cocotb/interfaces/common_functions/bitbang.py
caravel_cocotb/interfaces/common_functions/common.h
caravel_cocotb/interfaces/common_functions/gpios.h
caravel_cocotb/interfaces/common_functions/irq_api.h
caravel_cocotb/interfaces/common_functions/la.h
caravel_cocotb/interfaces/common_functions/mgmt_gpio.h
caravel_cocotb/interfaces/common_functions/spi_master.h
caravel_cocotb/interfaces/common_functions/test_functions.py
caravel_cocotb/interfaces/common_functions/timer0.h
caravel_cocotb/interfaces/common_functions/uart_api.h
caravel_cocotb/interfaces/common_functions/user_space.h
caravel_cocotb/scripts/get_timeouts.py
caravel_cocotb/scripts/merge_coverage.py
caravel_cocotb/scripts/rerun_script_tamplate.py
caravel_cocotb/scripts/run_all_sdf.py
caravel_cocotb/scripts/test_defaults/test_defaults.py
caravel_cocotb/scripts/verify_cocotb/DockerProcess.py
caravel_cocotb/scripts/verify_cocotb/RunFlow.py
caravel_cocotb/scripts/verify_cocotb/RunRegression.py
caravel_cocotb/scripts/verify_cocotb/RunTest.py
caravel_cocotb/scripts/verify_cocotb/Test.py
caravel_cocotb/scripts/verify_cocotb/WriteDesignInfo.py
caravel_cocotb/scripts/verify_cocotb/check_git.py
caravel_cocotb/scripts/verify_cocotb/read_defines.py
caravel_cocotb-1.3.2.dist-info/METADATA
caravel_cocotb-1.3.2.dist-info/WHEEL
caravel_cocotb-1.3.2.dist-info/entry_points.txt
caravel_cocotb-1.3.2.dist-info/top_level.txt
caravel_cocotb-1.3.2.dist-info/RECORD
