Metadata-Version: 2.1
Name: caravel_cocotb
Version: 1.3.2
Summary: efabless caravel cocotb verification flow.
Classifier: Programming Language :: Python :: 3
Classifier: Intended Audience :: Developers
Classifier: Operating System :: POSIX :: Linux
Classifier: Operating System :: MacOS :: MacOS X
Requires-Python: >3.7
Requires-Dist: PyYAML>=6
Requires-Dist: anytree<3,>=2.12.0
Requires-Dist: click>=8
Requires-Dist: cocotb<2,>=1.9.0
Requires-Dist: cocotb-coverage==1.1.0
Requires-Dist: oyaml==1.0
Requires-Dist: prettytable<4,>=3.7.0
Requires-Dist: rich<14,>=12
Requires-Dist: ruamel.yaml>=0.18.6
Requires-Dist: volare>=0.18.0
Requires-Dist: tabulate
Requires-Dist: setuptools
